diffusor/__init__.py
diffusor/diffusor.py
diffusor-1.3.0.dist-info/entry_points.txt
diffusor-1.3.0.dist-info/LICENSE
diffusor-1.3.0.dist-info/WHEEL
diffusor-1.3.0.dist-info/METADATA
diffusor-1.3.0.dist-info/RECORD
