Metadata-Version: 2.1
Name: diffusor
Version: 1.3.0
Summary: A pure-python diffing utility using Google's diff-match-patch.
Home-page: https://github.com/kobaltcore/diffusor
License: MIT
Author: CobaltCore
Author-email: cobaltcore@yandex.com
Requires-Python: >=3.7,<4.0
Classifier: License :: OSI Approved :: MIT License
Classifier: Programming Language :: Python :: 3
Classifier: Programming Language :: Python :: 3.7
Classifier: Programming Language :: Python :: 3.8
Classifier: Programming Language :: Python :: 3.9
Requires-Dist: PyYAML (>=5.4.1,<6.0.0)
Requires-Dist: click (>=7.1.2,<8.0.0)
Requires-Dist: diff-match-patch (>=20200713,<20200714)
Requires-Dist: logzero (>=1.7.0,<2.0.0)
Requires-Dist: pyyaml (>=5.3.1,<6.0.0)
Project-URL: Repository, https://github.com/kobaltcore/diffusor
